tests/__init__.py
tests/test_core.py
tests/test_core_vpm.py
tests/test_decision_manifold.py
tests/test_extract_critical_tile.py
tests/test_finance_fx_pipeline.py
tests/test_finance_tesla_pipeline.py
tests/test_finance_tesla_trading.py
tests/test_finance_tesla_trading2.py
tests/test_finance_tesla_trading3.py
tests/test_gif_epochs.py
tests/test_gif_epochs_better.py
tests/test_gif_logger.py
tests/test_gif_logging.py
tests/test_hash.py
tests/test_heartbeat.py
tests/test_heirarchy.py
tests/test_hierarchical.py
tests/test_hierarchical_comprehensive.py
tests/test_hierarchical_demo.py
tests/test_hierarchical_view_unit.py
tests/test_hunter.py
tests/test_image.py
tests/test_memory.py
tests/test_nonlinearity.py
tests/test_nonlinearity_auto.py
tests/test_organization.py
tests/test_performance.py
tests/test_pipeline_core_prepare.py
tests/test_pipeline_executor.py
tests/test_pipeline_gif_logging.py
tests/test_pipeline_new_stages.py
tests/test_pipeline_stages.py
tests/test_pipeline_stream.py
tests/test_png_text.py
tests/test_provenance_model.py
tests/test_quickstart.py
tests/test_receipts.py
tests/test_resolution_independence.py
tests/test_spatial_optimizer.py
tests/test_stdm_bimodal.py
tests/test_stdm_integration.py
tests/test_tensor_vpm_roundtrip.py
tests/test_titanic.py
tests/test_training_heartbeat_visualizer.py
tests/test_vpf_image_provenance.py
tests/test_vpm.py
tests/test_vpm_explain.py
tests/test_vpm_image_reader.py
tests/test_vpm_logic_diagonal_demo.py
tests/test_vpm_logic_operations.py
tests/test_vpm_metadata.py
tests/test_vpm_metadata_suite.py
tests/test_vpm_pyramid.py
tests/test_workflow.py
tests/test_world_scale_pyramid_io.py
tests/test_xor.py
tests/test_zeromemory.py
tests/text_performance.py
tests/utils.py
zeromodel/__init__.py
zeromodel/config.py
zeromodel/constants.py
zeromodel/core.py
zeromodel/edge.py
zeromodel/hierarchical.py
zeromodel/hierarchical_edge.py
zeromodel/memory.py
zeromodel/metadata.py
zeromodel/normalizer.py
zeromodel/png_text.py
zeromodel-1.0.8.dist-info/licenses/LICENSE
zeromodel-1.0.8.dist-info/METADATA
zeromodel-1.0.8.dist-info/WHEEL
zeromodel-1.0.8.dist-info/entry_points.txt
zeromodel-1.0.8.dist-info/top_level.txt
zeromodel-1.0.8.dist-info/RECORD
