Metadata-Version: 2.4
Name: ZeroModel
Version: 1.0.8
Summary: ZeroModel: Data-centric AI with visual policy maps
Home-page: https://github.com/ernanhughes/zeromodel
Author: Ernan Hughes
Author-email: ernanhughes@gmail.com
Keywords: ai,machine learning,explainability,vpm,provenance
Classifier: Development Status :: 3 - Alpha
Classifier: Intended Audience :: Developers
Classifier: Intended Audience :: Science/Research
Classifier: License :: OSI Approved :: MIT License
Classifier: Operating System :: OS Independent
Classifier: Programming Language :: Python :: 3
Classifier: Programming Language :: Python :: 3.7
Classifier: Programming Language :: Python :: 3.8
Classifier: Programming Language :: Python :: 3.9
Classifier: Programming Language :: Python :: 3.10
Classifier: Topic :: Scientific/Engineering :: Artificial Intelligence
Classifier: Topic :: Software Development :: Libraries :: Python Modules
Requires-Python: >=3.7
License-File: LICENSE
Requires-Dist: numpy>=1.20.0
Requires-Dist: PyWavelets>=1.1.1
Requires-Dist: pyyaml
Requires-Dist: duckdb>=0.6.2
Requires-Dist: pypng>=0.20210329
Requires-Dist: pyarrow
Requires-Dist: scipy
Requires-Dist: scikit-learn>=0.24.0
Requires-Dist: pillow
Provides-Extra: dev
Requires-Dist: pytest>=6.0; extra == "dev"
Requires-Dist: matplotlib>=3.4.0; extra == "dev"
Requires-Dist: imageio>=2.9.0; extra == "dev"
Requires-Dist: pandas>=1.2.0; extra == "dev"
Requires-Dist: ipykernel>=5.3.0; extra == "dev"
Requires-Dist: imageio[ffmpeg]>=2.9.0; extra == "dev"
Requires-Dist: tensorflow>=2.4.0; extra == "dev"
Requires-Dist: seaborn>=0.11.0; extra == "dev"
Requires-Dist: boto3; extra == "dev"
Dynamic: author
Dynamic: author-email
Dynamic: classifier
Dynamic: description
Dynamic: description-content-type
Dynamic: home-page
Dynamic: keywords
Dynamic: license-file
Dynamic: provides-extra
Dynamic: requires-dist
Dynamic: requires-python
Dynamic: summary
